{
  "last_updated": "2026-01-24T12:05:41.616255",
  "total_results": 9,
  "results": [
    {
      "game": "Superlotto 6/49",
      "game_type": "6/49",
      "date": "2026-01-01",
      "numbers": [
        23,
        30,
        19,
        18,
        41,
        21
      ],
      "jackpot": 86393934.3,
      "winners": 0
    },
    {
      "game": "Lotto 6/42",
      "game_type": "6/42",
      "date": "2026-01-01",
      "numbers": [
        34,
        35,
        38,
        1,
        18,
        41
      ],
      "jackpot": 5940000.0,
      "winners": 1
    },
    {
      "game": "6D Lotto",
      "game_type": "6D",
      "date": "2026-01-01",
      "numbers": [
        6,
        1,
        6,
        8,
        3,
        0
      ],
      "jackpot": 1034226.48,
      "winners": 0
    },
    {
      "game": "3D Lotto 2PM",
      "game_type": "3D-2PM",
      "date": "2026-01-01",
      "numbers": [
        6,
        7,
        5
      ],
      "jackpot": 4500.0,
      "winners": 25
    },
    {
      "game": "3D Lotto 5PM",
      "game_type": "3D-5PM",
      "date": "2026-01-01",
      "numbers": [
        6,
        9,
        5
      ],
      "jackpot": 4500.0,
      "winners": 89
    },
    {
      "game": "3D Lotto 9PM",
      "game_type": "3D-9PM",
      "date": "2026-01-01",
      "numbers": [
        5,
        0,
        7
      ],
      "jackpot": 4500.0,
      "winners": 278
    },
    {
      "game": "2D Lotto 2PM",
      "game_type": "2D-2PM",
      "date": "2026-01-01",
      "numbers": [
        7,
        10
      ],
      "jackpot": 4000.0,
      "winners": 92
    },
    {
      "game": "2D Lotto 5PM",
      "game_type": "2D-5PM",
      "date": "2026-01-01",
      "numbers": [
        25,
        2
      ],
      "jackpot": 4000.0,
      "winners": 56
    },
    {
      "game": "2D Lotto 9PM",
      "game_type": "2D-9PM",
      "date": "2026-01-01",
      "numbers": [
        7,
        21
      ],
      "jackpot": 4000.0,
      "winners": 210
    }
  ]
}